{"cameraMode":{"drawMode":0,"name":"Shaded","section":"Shading Mode"},"sceneLighting":true,"audioPlay":false,"sceneViewState":{"m_AlwaysRefresh":false,"showFog":true,"showSkybox":true,"showFlares":true,"showImageEffects":true,"showParticleSystems":true,"showVisualEffectGraphs":true,"m_FxEnabled":true},"in2DMode":false,"pivot":{"x":-25.02734375,"y":2.6897222995758058,"z":-7.314881801605225},"rotation":{"x":0.020315660163760186,"y":0.532127857208252,"z":-0.012773452326655388,"w":0.8463195562362671},"size":3.1907155513763429,"orthographic":false}